setup.py
Ingresse.egg-info/PKG-INFO
Ingresse.egg-info/SOURCES.txt
Ingresse.egg-info/dependency_links.txt
Ingresse.egg-info/requires.txt
Ingresse.egg-info/top_level.txt
ingresse/__init__.py