Metadata-Version: 1.1
Name: Ingresse
Version: 0.1
Summary: Ingresse Python SDK for great usage
Home-page: https://www.ingresse.com/
Author: Ingresse
Author-email: devel@ingresse.com
License: UNKNOWN
Platform: UNKNOWN
Classifier: Programming Language :: Python
Classifier: Development Status :: 1 - Planning
Classifier: Intended Audience :: Developers
Classifier: License :: OSI Approved :: MIT License
Classifier: Topic :: Software Development :: Libraries :: Python Modules
